habitat/__init__.py
habitat/habitat_cuda.cpython-39-x86_64-linux-gnu.so
habitat/utils.py
habitat/analysis/__init__.py
habitat/analysis/arguments.py
habitat/analysis/device.py
habitat/analysis/kernels.py
habitat/analysis/metrics.py
habitat/analysis/operation.py
habitat/analysis/predictor.py
habitat/analysis/run_time.py
habitat/analysis/trace.py
habitat/analysis/mlp/__init__.py
habitat/analysis/mlp/dataset.py
habitat/analysis/mlp/dataset_process.py
habitat/analysis/mlp/devices.csv
habitat/analysis/mlp/devices.py
habitat/analysis/mlp/mlp.py
habitat/analysis/mlp/train.py
habitat/analysis/wave_scaling/__init__.py
habitat/analysis/wave_scaling/common.py
habitat/analysis/wave_scaling/metadata.py
habitat/analysis/wave_scaling/resimplified.py
habitat/analysis/wave_scaling/roofline.py
habitat/analysis/wave_scaling/unified.py
habitat/data/__init__.py
habitat/data/devices.yml
habitat/data/kernels.sqlite
habitat/data/batch_norm/model.pth
habitat/data/bmm/model.pth
habitat/data/conv2d/model.pth
habitat/data/conv_transpose2d/model.pth
habitat/data/linear/model.pth
habitat/data/lstm/model.pth
habitat/profiling/__init__.py
habitat/profiling/autograd.py
habitat/profiling/backward.py
habitat/profiling/kernel.py
habitat/profiling/operation.py
habitat/profiling/run_time.py
habitat/tracking/__init__.py
habitat/tracking/base.py
habitat/tracking/callable.py
habitat/tracking/hook_manager.py
habitat/tracking/operation.py
deepview_predict-0.2.0.dist-info/METADATA
deepview_predict-0.2.0.dist-info/WHEEL
deepview_predict-0.2.0.dist-info/top_level.txt
deepview_predict-0.2.0.dist-info/RECORD
